jupyterlab_imarkdown/__init__.py
jupyterlab_imarkdown/_version.py
jupyterlab_imarkdown/labextension/build_log.json
jupyterlab_imarkdown/labextension/package.json
jupyterlab_imarkdown/labextension/static/747.08e3a8cd4289fcdacd8e.js
jupyterlab_imarkdown/labextension/static/747.39ae50eb4864920a275b.js
jupyterlab_imarkdown/labextension/static/814.5c9e87ee5e1d31b144d7.js
jupyterlab_imarkdown/labextension/static/929.331b90b6b0f1b60ce9db.js
jupyterlab_imarkdown/labextension/static/929.7b2ffc10371dd943610b.js
jupyterlab_imarkdown/labextension/static/lib_index_js.1de467d43bb4c4c12848.js
jupyterlab_imarkdown/labextension/static/lib_index_js.1de467d43bb4c4c12848.js.map
jupyterlab_imarkdown/labextension/static/lib_index_js.249cb2c99b5a834d12c9.js
jupyterlab_imarkdown/labextension/static/lib_index_js.249cb2c99b5a834d12c9.js.map
jupyterlab_imarkdown/labextension/static/lib_index_js.26bbd0fe454b408722b9.js
jupyterlab_imarkdown/labextension/static/lib_index_js.26bbd0fe454b408722b9.js.map
jupyterlab_imarkdown/labextension/static/lib_index_js.2abc76d42e984a058657.js
jupyterlab_imarkdown/labextension/static/lib_index_js.2abc76d42e984a058657.js.map
jupyterlab_imarkdown/labextension/static/lib_index_js.2b234769cf5224a7afbe.js
jupyterlab_imarkdown/labextension/static/lib_index_js.2b234769cf5224a7afbe.js.map
jupyterlab_imarkdown/labextension/static/lib_index_js.35006a3eaf0960bf2abd.js
jupyterlab_imarkdown/labextension/static/lib_index_js.35006a3eaf0960bf2abd.js.map
jupyterlab_imarkdown/labextension/static/lib_index_js.3ba16ce4000e21519847.js
jupyterlab_imarkdown/labextension/static/lib_index_js.3ba16ce4000e21519847.js.map
jupyterlab_imarkdown/labextension/static/lib_index_js.3ccb1db57fad3db621e8.js
jupyterlab_imarkdown/labextension/static/lib_index_js.3ccb1db57fad3db621e8.js.map
jupyterlab_imarkdown/labextension/static/lib_index_js.42f3f203973988a24f57.js
jupyterlab_imarkdown/labextension/static/lib_index_js.42f3f203973988a24f57.js.map
jupyterlab_imarkdown-0.2.0.dist-info/LICENSE
jupyterlab_imarkdown-0.2.0.dist-info/METADATA
jupyterlab_imarkdown-0.2.0.dist-info/WHEEL
jupyterlab_imarkdown-0.2.0.dist-info/top_level.txt
jupyterlab_imarkdown-0.2.0.dist-info/RECORD
