Metadata-Version: 2.1
Name: jupyterlab-imarkdown
Version: 0.2.0
Summary: A JupyterLab extension to render expressions given in Markdown.
Home-page: https://github.com/agoose77/jupyterlab-imarkdown
Author: Angus Hollands
Author-email: goosey15@gmail.com
License: BSD-3-Clause
Keywords: Jupyter,JupyterLab,JupyterLab3
Platform: Linux
Platform: Mac OS X
Platform: Windows
Classifier: License :: OSI Approved :: BSD License
Classifier: Programming Language :: Python
Classifier: Programming Language :: Python :: 3
Classifier: Programming Language :: Python :: 3.6
Classifier: Programming Language :: Python :: 3.7
Classifier: Programming Language :: Python :: 3.8
Classifier: Programming Language :: Python :: 3.9
Classifier: Framework :: Jupyter
Classifier: Framework :: Jupyter :: JupyterLab
Classifier: Framework :: Jupyter :: JupyterLab :: 3
Classifier: Framework :: Jupyter :: JupyterLab :: Extensions
Classifier: Framework :: Jupyter :: JupyterLab :: Extensions :: Prebuilt
Requires-Python: >=3.6
License-File: LICENSE
Provides-Extra: examples
Requires-Dist: sympy (>=1.0.0) ; extra == 'examples'
Requires-Dist: ipywidgets (>=7.0.0) ; extra == 'examples'
Requires-Dist: numpy (>=1.17) ; extra == 'examples'
Requires-Dist: jupyterlab-markup-expr (>=0.1.1) ; extra == 'examples'
